
[
  {
    "description": "கீழ்க்காணும் சொற்களில் எது உயர்திணை அல்லாதது?",
    "options": [
      "a) முகிலன்",
      "b) தலைவி",
      "c) புத்தகம்",
      "d) ஆசிரியர்"
    ],
    "answer": "c"
  },
  {
    "description": "\"முக்கனி\" என்ற தொகைச் சொல்லில் உள்ள மூன்று கனிகள் எவை?",
    "options": [
      "a) வாழைப்பழம், மாங்காய், தென்னைப்பழம்",
      "b) மாங்காய், பலாப்பழம், தென்னைப்பழம்",
      "c) மாங்காய், வாழைப்பழம், கொய்யாப்பழம்",
      "d) வாழைப்பழம், மாங்காய், கொய்யாப்பழம்"
    ],
    "answer": "a"
  },
  {
    "description": "\"நாற்று வைப்பர்\" என்ற வரியில் \"வைப்பர்\" என்ற சொல்லின் இரண்டாவது பொருள் என்ன?",
    "options": [
      "a) விதை விதைத்தல்",
      "b) மெதுவாக வைத்தல்",
      "c) மண் அள்ளுதல்",
      "d) விதை பூத்து மலர்ந்தல்"
    ],
    "answer": "b"
  },
  {
    "description": "கீழ்க்காணும் சொற்களில் எது \"மொழியியல்\" என்ற கலைச்சொல்லின் ஆங்கிலச் சொல்லாகும்?",
    "options": [
      "a) Literature",
      "b) Linguistics",
      "c) Journalism",
      "d) Phonology"
    ],
    "answer": "b"
  },
  {
    "description": "\"தொகைச் சொற்களை விரித்து எழுதுக\" என்ற பகுதியில் கொடுக்கப்பட்டுள்ள எடுத்துக்காட்டில் இருந்து \"ஐந்திணை\" என்ற தொகைச் சொல்லில் இல்லாதது எது?",
    "options": [
      "a) மன்னன்",
      "b) வணிகன்",
      "c) வேடர்",
      "d) குரு"
    ],
    "answer": "d"
  },
  {
    "description": "\"என் பொறுப்புகள்...\" என்ற பகுதியில் கொடுக்கப்பட்டுள்ள பொறுப்புகளில் எது தாய்மொழியின் வளர்ச்சிக்கு உதவும்?",
    "options": [
      "a) கடிதங்கள் எழுதுதல்",
      "b) பொம்மலாட்டத்தைப் போற்றுதல்",
      "c) தெருக்கூத்தைப் போற்றுதல்",
      "d) திருத்தமான மொழிநடையைப் பயன்படுத்துதல்"
    ],
    "answer": "d"
  }
]

[
  {
    "description": "“மொழி பற்றிய விளக்கம் – தாய்மொழி – தாய்மொழிப் பற்று - தாய்மொழிப் பற்றுக் கொண்ட சான்றோர் – சாதுவன் வரலாறு – நமது கடமை – முடிவுரை”  என்பவை எந்தக் கட்டுரையின்  முக்கியப் பகுதிகள்?",
    "options": [
      "தாய்மொழிப் பற்று",
      "மொழியோடு விளையாடு",
      "என் பொறுப்புகள்...",
      "கலைச்சொல் அறிவோம்"
    ],
    "answer": "A"
  },
  {
    "description": "கீழ்க்காணும் சொற்களில் எது உயர்திணை அல்ல?",
    "options": [
      "முகிலன்",
      "தலைவி",
      "புத்தகம்",
      "ஆசிரியர்"
    ],
    "answer": "C"
  },
  {
    "description": "\"முக்கனி\" என்ற தொகைச்சொல் எதை குறிக்கிறது?",
    "options": [
      "மாங்காய், வாழைப்பழம், தென்னைப்பழம்",
      "இலக்கணம், இலக்கியம், வானவியல்",
      "கிழக்கு, மேற்கு, தெற்கு, வடக்கு",
      "கடவுள், மன்னன், வணிகன், விவசாயி, வேடர்"
    ],
    "answer": "A"
  },
  {
    "description": "\"வயலுக்குச் செல்வர்\" என்ற இரு பொருள் கொண்ட சொல் எந்த வாக்கியத்தில் பயன்படுத்தப்பட்டுள்ளது?",
    "options": [
      "மழலை பேசும் _______ அழகு. (இனிமைத் தமிழ்)",
      "அன்னை தந்தையின் கைப்பிடித்துக் குழந்தை _______ பழகும்.",
      "அறிஞர் அண்ணாவின் சிறப்பு அவரது அடுக்கு மொழி _______.",
      "நீ அறிந்ததைப் பிறருக்குச் _______. (சொல்)"
    ],
    "answer": "B"
  },
  {
    "description": "கீழ்க்காணும் எது \"பொம்மலாட்டம்\"  என்ற சொல்லுக்கு இணையான கலைச்சொல்?",
    "options": [
      "ஊடகம்",
      "ஒலியியல்",
      "நேக்கம்",
      "Puppetry"
    ],
    "answer": "D"
  },
  {
    "description": "கட்டுரை எழுதும்போது திருத்தமான மொழி நடையை கையாள வேண்டும் என்பது எந்தப் பொறுப்பை குறிக்கிறது?",
    "options": [
      "கலைச்சொல் அறிவோம்",
      "என் பொறுப்புகள்...",
      "இணையத்தில் காண்க",
      "மொழியோடு விளையாடு"
    ],
    "answer": "B"
  }
]

[
  {
    "description": "“வயல்” என்ற சொல்லுடன் தொடர்புடையது எது?",
    "options": ["முகிலன்", "குதிரை", "தலைவி", "அஃறிணை"],
    "answer": ["D"]
  },
  {
    "description": "“தாய்மொழிப் பற்று” என்ற தலைப்பில் உள்ள கட்டுரையில் குறிப்பிடப்பட்டுள்ள ஒரு சான்றோர் யார்?",
    "options": ["சாதுவன்", "திருவள்ளுவர்", "கம்பர்", "பாரதியார்"],
    "answer": ["A"]
  },
  {
    "description": "“முத்தமிழ்” என்பது என்னவாக விரிவடையும்?",
    "options": ["இலக்கணம், இலக்கியம், நாடகம்", "இலக்கணம், இலக்கியம், வானவியல்", "இலக்கணம், இலக்கியம், மருத்துவம்", "இலக்கணம், இலக்கியம், சங்கீதம்"],
    "answer": ["D"]
  },
  {
    "description": "“வழக்கு” என்ற சொல் இரண்டு பொருள்களைத் தருகிறது. அவற்றில் எது சரியானது?",
    "options": ["நீதிமன்றத்தில் தொடுப்பது", "சமூக வழக்கம்", "பொதுவான நடைமுறை", "இவையனைத்தும்"],
    "answer": ["D"]
  },
  {
    "description": "“ஊடகம்” என்பதற்கான கலைச்சொல் என்ன?",
    "options": ["Communication", "Media", "Journalism", "Linguistics"],
    "answer": ["B"]
  },
  {
    "description": "_______ என்பது உயர்திணை, அஃறிணை என இரு வகைப்படும்.",
    "options": ["சொல்", "கதை", "நூல்", "நேரம்"],
    "answer": ["A"]
  },
  {
    "description": "தாய்மொழிப் பற்று என்பது நம் _______ மீதான அன்பும் பக்தியும்.",
    "options": ["நாடு", "நண்பர்", "மொழி", "கலாச்சாரம்"],
    "answer": ["C"]
  },
  {
    "description": "______ என்ற சொல் இனிமைத் தமிழ் என்ற பொருளையும், மழலை என்ற பொருளையும் கொண்டுள்ளது.",
    "options": ["மழலை", "பூ", "கண்", "வீடு"],
    "answer": ["A"]
  },
  {
    "description": "பொம்மலாட்டம், தெருக்கூத்து போன்றவை _______ கலைகள்.",
    "options": ["சினிமா", "நாட்டுப்புற", "இசை", "நாடகம்"],
    "answer": ["B"]
  },
  {
    "description": "______ என்பது மொழியின் ஒலியியல் அம்சங்களை ஆராய்வது.",
    "options": ["இலக்கணம்", "ஒலியியல்", "மொழியியல்", "இலக்கியம்"],
    "answer": ["B"]
  }
]

[
    {
        "description": "கீழே கொடுக்கப்பட்டுள்ளவற்றில் எது தாய்மொழிப் பற்றுக்கான உதாரணம்?",
        "options": [
            "ஒருவர் தனது தாய்மொழியில் தான் உணர்வுகளை வெளிப்படுத்த விரும்புவது.",
            "ஒருவர் தனது தாய்மொழியைப் பற்றி எந்த அறிவும் இல்லாமல் இருப்பது.",
            "ஒருவர் தனது தாய்மொழியை விட வேறு மொழிகளில் பேசுவதில் ஆர்வம் காட்டுவது.",
            "ஒருவர் தனது தாய்மொழியைப் பற்றி எந்த அக்கறையும் இல்லாமல் இருப்பது."
        ],
        "answer": "A"
    },
    {
        "description": "\"ஐந்திணை\" என்ற சொல்லை விரித்து எழுதுக.",
        "options": [
            "அறம், பொருள், இன்பம், வீடு, மோட்சம்",
            "கடவுள், மன்னன், வணிகன், விவசாயி, வேடர்",
            "இலக்கணம், இலக்கியம், வானவியல், சிற்பம், ஓவியம்",
            "கிழக்கு, மேற்கு, தெற்கு, வடக்கு, நடு"
        ],
        "answer": "B"
    },
    {
        "description": "\"கயல்விழி\" என்ற சொல் எந்த இனத்தைச் சேர்ந்தது?",
        "options": [
            "உயர்திணை",
            "அஃறிணை",
            "இரண்டும்",
            "எதுவும் இல்லை"
        ],
        "answer": "B"
    },
    {
        "description": "\"வயலுக்குச் செல்வர்\" என்ற சொற்றொடரை \"அடுக்கு மொழி\" என்று அழைப்பது யார்?",
        "options": [
            "தலைவி",
            "ஆசிரியர்",
            "முகிலன்",
            "அறிஞர் அண்ணா"
        ],
        "answer": "D"
    },
    {
        "description": "\"இரு பொருள் கொண்ட சொல்\" என்ற கருத்தை எடுத்துக்காட்டும் சொற்றொடர் எது?",
        "options": [
            "மழலை பேசும் இனிமைத் தமிழ்.",
            "அன்னை தந்தையின் கைப்பிடித்துக் குழந்தை வயலுக்குச் செல்வர்.",
            "நீ அறிந்ததைப் பிறருக்குச் சொல்.",
            "நீதி மன்றத்தில் தொடுப்பது வழக்கு."
        ],
        "answer": "D"
    },
    {
        "description": "கீழ்க்கண்டவற்றில் எது \"நேக்கம்\" என்ற கலைச்சொல்லின் பொருள்?",
        "options": [
            "ஒலியியல்",
            "எழுத்துரு",
            "ஊடகம்",
            "மொழியியல்"
        ],
        "answer": "B"
    },
    {
        "description": "தொகைச் சொற்களை விரித்து எழுதுவது எந்த மொழி நடையை வளர்க்க உதவும்?",
        "options": [
            "அறிவியல் நடை",
            "செய்தி நடை",
            "கவிதை நடை",
            "இலக்கிய நடை"
        ],
        "answer": "D"
    },
    {
        "description": "\"தாய்மொழிப் பற்று\" என்பது என்ன?",
        "options": [
            "ஒருவரது தாய்க்கு மரியாதை செலுத்துவது.",
            "தனது தாயின் மொழியைப் பாதுகாப்பது.",
            "ஒருவர் தனது தாய்மொழியில் பெருமை கொள்வது.",
            "ஒருவர் தனது தாய்மொழியைப் பயன்படுத்தி மற்ற மொழிகளைக் கற்றுக்கொள்வது."
        ],
        "answer": "C"
    }
]

[
  {
    "description": "கீழ்க்காணும் சொற்களில் எது உயர்திணை அல்லாதது?",
    "options": [
      "a) முகிலன்",
      "b) தலைவி",
      "c) கடல்",
      "d) ஆசிரியர்"
    ],
    "answer": "C"
  },
  {
    "description": "\"ஐந்திணை\" என்ற தொகைச் சொல்லின் விரிவாக்கம் எது?",
    "options": [
      "a) மாங்காய், வாழைப்பழம், தென்னைப்பழம்",
      "b) இலக்கணம், இலக்கியம், வானவியல்",
      "c) கிழக்கு, மேற்கு, தெற்கு, வடக்கு",
      "d) கடவுள், மன்னன், வணிகன், விவசாயி, வேடர்"
    ],
    "answer": "D"
  },
  {
    "description": "\"வயலுக்குச் செல்வர்\" என்ற சொற்றொடரில் இரண்டு பொருள் தரும் சொல் எது?",
    "options": [
      "a) வயல்",
      "b) செல்வர்",
      "c) குழந்தை",
      "d) அன்னை தந்தை"
    ],
    "answer": "B"
  },
  {
    "description": "\"நீச்சத் தண்ணி குடி\" என்ற சொற்றொடர் எந்த வகையான பேச்சு வழக்கு?",
    "options": [
      "a) அறிஞர்களின் பேச்சு வழக்கு",
      "b) நாட்டுப்புறப் பேச்சு வழக்கு",
      "c) நகரப் பேச்சு வழக்கு",
      "d) மதப் பேச்சு வழக்கு"
    ],
    "answer": "B"
  },
  {
    "description": "\"மொழியோடு விளையாடு\" என்ற பகுதியில் கொடுக்கப்பட்டுள்ள \"இருதிணை\" என்ற தொகைச் சொல்லின் விரிவாக்கம் என்ன?",
    "options": [
      "a) உயர்திணை, அஃறிணை",
      "b) மனிதர், விலங்கு",
      "c) ஆண், பெண்",
      "d) நல்லது, கெட்டது"
    ],
    "answer": "A"
  },
  {
    "description": "\"கலைச்சொல் அறிவோம்\" என்ற பகுதியில் \"Media\" என்ற ஆங்கிலச் சொல்லின் தமிழாக்கம் எது?",
    "options": [
      "a) மொழியியல்",
      "b) ஒலியியல்",
      "c) ஊடகம்",
      "d) இதழியல்"
    ],
    "answer": "C"
  },
  {
    "description": "\"தாய்மொழிப் பற்று\" என்ற பகுதியில் குறிப்பிடப்பட்டுள்ள \"சாதுவன்\" யார்?",
    "options": [
      "a) ஒரு மொழி அறிஞர்",
      "b) ஒரு வீரன்",
      "c) ஒரு கவிஞர்",
      "d) ஒரு அரசன்"
    ],
    "answer": "C"
  },
  {
    "description": "\"என் பொறுப்புகள்...\" என்ற பகுதியில் குறிப்பிடப்பட்டுள்ள பொம்மலாட்டம், தெருக்கூத்து போன்றவை எந்த வகையான கலைகள்?",
    "options": [
      "a) நாடகக் கலை",
      "b) இசைக் கலை",
      "c) சிற்பக் கலை",
      "d) நாட்டுப்புறக் கலை"
    ],
    "answer": "D"
  },
  {
    "description": "\"கலைச்சொல் அறிவோம்\" என்ற பகுதியில் கொடுக்கப்பட்டுள்ள \"Puppetry\" என்ற ஆங்கிலச் சொல்லின் தமிழாக்கம் எது?",
    "options": [
      "a) மொழியியல்",
      "b) ஒலியியல்",
      "c) ஊடகம்",
      "d) பொம்மலாட்டம்"
    ],
    "answer": "D"
  },
  {
    "description": "\"மொழியோடு விளையாடு\" பகுதியில் கொடுக்கப்பட்டுள்ள \"நாற்றிசை\" என்ற தொகைச் சொல்லின் விரிவாக்கத்தில் எது இல்லை?",
    "options": [
      "a) வடக்கு",
      "b) தெற்கு",
      "c) மேற்கு",
      "d) கிழக்கு"
    ],
    "answer": "A"
  }
]

[
    {
        "description": "“முகிலன்” என்ற சொல், “தலைவி” என்ற சொல்லைப் போலவே, யாரைப் பற்றிய சொல்லாகும்?",
        "options": [
            "a) விலங்கைப் பற்றிய சொல்",
            "b) இயற்கைப் பொருளைப் பற்றிய சொல்",
            "c) ஒருவரைப் பற்றிய சொல்",
            "d) பொருளைப் பற்றிய சொல்"
        ],
        "answer": "C"
    },
    {
        "description": "“வயல்”, “குதிரை”, “கடல்” ஆகியவற்றைப் பற்றிய சொற்களின் பொதுவான இயல்பு என்ன?",
        "options": [
            "a) இவை அனைத்தும் உயிரற்றவை",
            "b) இவை அனைத்தும் உயிர் உள்ளவை",
            "c) இவை அனைத்தும் இயற்கையைப் பற்றியவை",
            "d) இவை அனைத்தும் மனிதர்களைப் பற்றியவை"
        ],
        "answer": "A"
    },
    {
        "description": "“முக்கனி” என்பது _______ சொல்லுக்கு ஒரு உதாரணம்.",
        "options": [
            "a) இணைச்சொல்",
            "b) தொகைச்சொல்",
            "c) வினைச்சொல்",
            "d) பெயர்ச்சொல்"
        ],
        "answer": "B"
    },
    {
        "description": "“ஐந்திணை” என்ற தொகைச் சொல்லில் உள்ள ஐந்து வகைகளில், “வேடர்” எந்த வகையைச் சேர்ந்தவர்?",
        "options": [
            "a) கடவுள்",
            "b) மன்னன்",
            "c) வணிகன்",
            "d) வேடர்"
        ],
        "answer": "D"
    },
    {
        "description": "“நாற்றிசை” என்ற தொகைச் சொல்லை விரித்து எழுதும்போது, “மேற்கு” என்ற சொல்லுக்கு இணையான சொல் எது?",
        "options": [
            "a) வடக்கு",
            "b) தெற்கு",
            "c) கிழக்கு",
            "d) மேற்கு"
        ],
        "answer": "D"
    },
    {
        "description": "“மழலை” என்ற சொல் எந்த இரண்டு பொருள்களைக் குறிக்கும்?",
        "options": [
            "a) குழந்தை, இனிமை",
            "b) அழகு, குழந்தை",
            "c) தமிழ், மொழி",
            "d) இனிமை, தமிழ்"
        ],
        "answer": "A"
    },
    {
        "description": "“வயலுக்குச் செல்வர்” என்ற சொற்றொடரில் உள்ள “வயல்” என்பதற்கு இரண்டு பொருள்கள் உள்ளன. அவற்றில் ஒன்று “நிலம்” என்பது. மற்றொரு பொருள் எது?",
        "options": [
            "a) தோட்டம்",
            "b) மலை",
            "c) காடு",
            "d) கடல்"
        ],
        "answer": "A"
    },
    {
        "description": "“சொல்” என்பதற்கு இரண்டு பொருள்கள் உள்ளன. அவற்றில் ஒன்று “வாக்கு” என்பது. மற்றொரு பொருள் எது?",
        "options": [
            "a) மொழி",
            "b) எழுத்து",
            "c) வார்த்தை",
            "d) இலக்கியம்"
        ],
        "answer": "B"
    },
    {
        "description": "“வழக்கு” என்ற சொல்லின் இரண்டு பொருள்களில் ஒன்று “நீதிமன்றத்தில் தொடுப்பது” என்பது. மற்றொரு பொருள் எது?",
        "options": [
            "a) வழக்கம்",
            "b) பழக்கம்",
            "c) நடைமுறை",
            "d) முறை"
        ],
        "answer": "A"
    },
    {
        "description": "“ஊடகம்” என்ற கலைச்சொல்லின் ஆங்கிலச் சொல் எது?",
        "options": [
            "a) Linguistics",
            "b) Journalism",
            "c) Media",
            "d) Puppetry"
        ],
        "answer": "C"
    }
]
